{
    "id": "powerhouse/subgraph",
    "name": "Subgraph Module",
    "extension": ".phdm",
    "description": "",
    "author": {
        "name": "Powerhouse",
        "website": "https://powerhouse.inc"
    },
    "specifications": [
        {
            "version": 1,
            "changeLog": [],
            "state": {
                "global": {
                    "schema": "type SubgraphModuleState {\n  name: String!\n  status: StatusType!\n}\n\nenum StatusType {\n  DRAFT\n  CONFIRMED\n}",
                    "initialValue": "{\n  \"name\": \"\",\n  \"status\": \"DRAFT\"\n}",
                    "examples": []
                },
                "local": {
                    "schema": "",
                    "initialValue": "",
                    "examples": []
                }
            },
            "modules": [
                {
                    "id": "8af5bda9-6fc7-4427-bfed-1d32d76a552f",
                    "name": "base_operations",
                    "description": "",
                    "operations": [
                        {
                            "id": "d7cd6b6b-01ea-42c8-97e2-288e04b50b42",
                            "name": "SET_SUBGRAPH_NAME",
                            "description": "",
                            "schema": "input SetSubgraphNameInput {\n  name: String!\n}",
                            "template": "",
                            "reducer": "",
                            "errors": [],
                            "examples": [],
                            "scope": "global"
                        },
                        {
                            "id": "5a20e641-dc36-428e-8924-ecb07f3f1b94",
                            "name": "SET_SUBGRAPH_STATUS",
                            "description": "",
                            "schema": "input SetSubgraphStatusInput {\n  status: StatusType!\n}",
                            "template": "",
                            "reducer": "",
                            "errors": [],
                            "examples": [],
                            "scope": "global"
                        }
                    ]
                }
            ]
        }
    ]
}